LICENSE
README.md
setup.py
distquant/__init__.py
distquant/distquant.py
distquant.egg-info/PKG-INFO
distquant.egg-info/SOURCES.txt
distquant.egg-info/dependency_links.txt
distquant.egg-info/requires.txt
distquant.egg-info/top_level.txt